CHANGES.txt
CONTRIBUTORS.txt
MANIFEST.in
README.txt
setup.cfg
setup.py
zgeo/__init__.py
zgeo.recipe.openlayers.egg-info/PKG-INFO
zgeo.recipe.openlayers.egg-info/SOURCES.txt
zgeo.recipe.openlayers.egg-info/dependency_links.txt
zgeo.recipe.openlayers.egg-info/entry_points.txt
zgeo.recipe.openlayers.egg-info/namespace_packages.txt
zgeo.recipe.openlayers.egg-info/not-zip-safe
zgeo.recipe.openlayers.egg-info/requires.txt
zgeo.recipe.openlayers.egg-info/top_level.txt
zgeo/recipe/__init__.py
zgeo/recipe/openlayers/README.txt
zgeo/recipe/openlayers/__init__.py
zgeo/recipe/openlayers/testdata/README.txt
zgeo/recipe/openlayers/tests/__init__.py
zgeo/recipe/openlayers/tests/test_docs.py