Metadata-Version: 1.0
Name: zgeo.recipe.openlayers
Version: 0.2
Summary: Build standard or custom profiles of the OpenLayers library
Home-page: http://bitbucket.org/sgillies/zgeorecipeopenlayers/
Author: Sean Gillies
Author-email: sean.gillies@gmail.com
License: GPL
Keywords: buildout recipe openlayers
Platform: UNKNOWN
Classifier: Framework :: Buildout
Classifier: Intended Audience :: Developers
Classifier: Topic :: Software Development :: Build Tools
Classifier: Topic :: Software Development :: Libraries :: Python Modules
Classifier: License :: OSI Approved :: GNU General Public License (GPL)
